Metadata-Version: 2.1
Name: cs453-dictionary-mrt
Version: 2.0.0
Summary: UNKNOWN
Author: Murat ANGIN
License: UNKNOWN
Platform: UNKNOWN
Requires-Python: >=3.8
Requires-Dist: requests (>=2.23.0)
